nexshell/__init__.py
nexshell/cli.py
nexshell-1.0.0.dist-info/licenses/LICENSE
nexshell-1.0.0.dist-info/METADATA
nexshell-1.0.0.dist-info/WHEEL
nexshell-1.0.0.dist-info/entry_points.txt
nexshell-1.0.0.dist-info/top_level.txt
nexshell-1.0.0.dist-info/RECORD
