Metadata-Version: 2.4
Name: nexshell
Version: 1.0.0
Summary: A beautiful and feature-rich AI-powered CLI chatbot using Google Gemini
Home-page: https://github.com/yourusername/nexshell
Author: NexShell Team
Author-email: NexShell Team <contact@nexshell.dev>
License: MIT
Project-URL: Homepage, https://github.com/yourusername/nexshell
Project-URL: Documentation, https://github.com/yourusername/nexshell#readme
Project-URL: Repository, https://github.com/yourusername/nexshell
Project-URL: Issues, https://github.com/yourusername/nexshell/issues
Keywords: chatbot,ai,gemini,cli,assistant,terminal,conversational-ai
Classifier: Development Status :: 5 - Production/Stable
Classifier: Intended Audience :: Developers
Classifier: Intended Audience :: End Users/Desktop
Classifier: Topic :: Communications :: Chat
Classifier: License :: OSI Approved :: MIT License
Classifier: Programming Language :: Python :: 3
Classifier: Operating System :: OS Independent
Requires-Python: >=3.7
License-File: LICENSE
Requires-Dist: google-generativeai>=0.3.0
Requires-Dist: python-dotenv>=1.0.0
Requires-Dist: colorama>=0.4.6
Dynamic: author
Dynamic: home-page
Dynamic: license-file
Dynamic: requires-python
